YoutubeVideoTrimmer/__init__.py
YoutubeVideoTrimmer-0.0.5.dist-info/LICENSE
YoutubeVideoTrimmer-0.0.5.dist-info/LICENSE.txt
YoutubeVideoTrimmer-0.0.5.dist-info/METADATA
YoutubeVideoTrimmer-0.0.5.dist-info/WHEEL
YoutubeVideoTrimmer-0.0.5.dist-info/top_level.txt
YoutubeVideoTrimmer-0.0.5.dist-info/zip-safe
YoutubeVideoTrimmer-0.0.5.dist-info/RECORD
