Metadata-Version: 2.1
Name: YoutubeVideoTrimmer
Version: 0.0.5
Summary: A compact solution for trimming YouTube videos You may get the desired output video clip by providing the YouTube video URL and required duration.
Home-page: https://www.karuwy.com/
Author: Arunkumar Palani
Author-email: arunkumarpas002@gmail.com
License: UNKNOWN
Keywords: youtube,download,video,stream,trimmer,youtube video trimmer,youtube video downloader,youtube video downloader and trimmer
Platform: UNKNOWN
Classifier: Programming Language :: Python :: 3.6
Classifier: Programming Language :: Python :: 3.7
Classifier: Programming Language :: Python :: 3.8
Classifier: Programming Language :: Python :: 3.9
Classifier: Programming Language :: Python
Classifier: License :: OSI Approved :: MIT License
Classifier: Operating System :: OS Independent
Classifier: Topic :: Internet
Classifier: Topic :: Multimedia :: Video
Classifier: Topic :: Software Development :: Libraries :: Python Modules
Classifier: Topic :: Terminals
Classifier: Topic :: Utilities
Classifier: Natural Language :: English
Classifier: Environment :: Console
Classifier: Environment :: Web Environment
License-File: LICENSE
License-File: LICENSE.txt
Requires-Dist: pytube
Requires-Dist: moviepy
